petthermotools/Barom.py
petthermotools/Compositions.py
petthermotools/GenFuncs.py
petthermotools/Holland.py
petthermotools/Installation.py
petthermotools/Liq.py
petthermotools/MELTS.py
petthermotools/Melting.py
petthermotools/Path.py
petthermotools/Path_wrappers.py
petthermotools/PhaseDiagrams.py
petthermotools/Plotting.py
petthermotools/Saturation.py
petthermotools/__init__.py
petthermotools/_version.py
petthermotools/core_config.py
petthermotools-0.3.20.dist-info/LICENSE.txt
petthermotools-0.3.20.dist-info/METADATA
petthermotools-0.3.20.dist-info/WHEEL
petthermotools-0.3.20.dist-info/top_level.txt
petthermotools-0.3.20.dist-info/RECORD
