Metadata-Version: 2.1
Name: petthermotools
Version: 0.3.20
Summary: petthermotools
Home-page: https://github.com/gleesonm1/PetThermoTools
Author: Matthew Gleeson
Author-email: gleesonm@berkeley.edu
License: UNKNOWN
Platform: UNKNOWN
Classifier: Programming Language :: Python :: 3
Classifier: Operating System :: OS Independent
Requires-Python: >=3.9
Requires-Dist: pandas
Requires-Dist: numpy
Requires-Dist: matplotlib
Requires-Dist: scikit-learn
Requires-Dist: scipy
Requires-Dist: tinynumpy
Requires-Dist: shapely
Requires-Dist: tqdm
Requires-Dist: psutil
